odoo/addons/module_prototyper/README.rst
odoo/addons/module_prototyper/__init__.py
odoo/addons/module_prototyper/__manifest__.py
odoo/addons/module_prototyper/data/README.rst
odoo/addons/module_prototyper/data/module_prototyper_api_version_data.xml
odoo/addons/module_prototyper/i18n/am.po
odoo/addons/module_prototyper/i18n/ar.po
odoo/addons/module_prototyper/i18n/bg.po
odoo/addons/module_prototyper/i18n/bs.po
odoo/addons/module_prototyper/i18n/ca.po
odoo/addons/module_prototyper/i18n/ca_ES.po
odoo/addons/module_prototyper/i18n/cs.po
odoo/addons/module_prototyper/i18n/da.po
odoo/addons/module_prototyper/i18n/da_DK.po
odoo/addons/module_prototyper/i18n/de.po
odoo/addons/module_prototyper/i18n/el_GR.po
odoo/addons/module_prototyper/i18n/en_AU.po
odoo/addons/module_prototyper/i18n/en_GB.po
odoo/addons/module_prototyper/i18n/es.po
odoo/addons/module_prototyper/i18n/es_AR.po
odoo/addons/module_prototyper/i18n/es_CL.po
odoo/addons/module_prototyper/i18n/es_CO.po
odoo/addons/module_prototyper/i18n/es_CR.po
odoo/addons/module_prototyper/i18n/es_DO.po
odoo/addons/module_prototyper/i18n/es_EC.po
odoo/addons/module_prototyper/i18n/es_ES.po
odoo/addons/module_prototyper/i18n/es_MX.po
odoo/addons/module_prototyper/i18n/es_PE.po
odoo/addons/module_prototyper/i18n/es_PY.po
odoo/addons/module_prototyper/i18n/es_VE.po
odoo/addons/module_prototyper/i18n/et.po
odoo/addons/module_prototyper/i18n/eu.po
odoo/addons/module_prototyper/i18n/fa.po
odoo/addons/module_prototyper/i18n/fi.po
odoo/addons/module_prototyper/i18n/fr.po
odoo/addons/module_prototyper/i18n/fr_CA.po
odoo/addons/module_prototyper/i18n/fr_CH.po
odoo/addons/module_prototyper/i18n/fr_FR.po
odoo/addons/module_prototyper/i18n/gl.po
odoo/addons/module_prototyper/i18n/gl_ES.po
odoo/addons/module_prototyper/i18n/he.po
odoo/addons/module_prototyper/i18n/hi.po
odoo/addons/module_prototyper/i18n/hr.po
odoo/addons/module_prototyper/i18n/hr_HR.po
odoo/addons/module_prototyper/i18n/hu.po
odoo/addons/module_prototyper/i18n/id.po
odoo14_addon_module_prototyper-14.0.1.0.1.dist-info/METADATA
odoo14_addon_module_prototyper-14.0.1.0.1.dist-info/WHEEL
odoo14_addon_module_prototyper-14.0.1.0.1.dist-info/top_level.txt
odoo14_addon_module_prototyper-14.0.1.0.1.dist-info/RECORD
